MANIFEST.in
setup.py
Roomba980_Python.egg-info/PKG-INFO
Roomba980_Python.egg-info/SOURCES.txt
Roomba980_Python.egg-info/dependency_links.txt
Roomba980_Python.egg-info/entry_points.txt
Roomba980_Python.egg-info/requires.txt
Roomba980_Python.egg-info/top_level.txt
res/binfull.png
res/home.png
res/map.png
res/roomba-base.png
res/roomba-charge.png
res/roomba.png
res/roombacancelled.png
res/roombaerror.png
roomba/__init__.py
roomba/getpassword.py
roomba/roomba.py