Metadata-Version: 1.0
Name: Roomba980-Python
Version: 1.2.1
Summary: Python program and library to control iRobot Roomba 980 Vacuum Cleaner
Home-page: https://github.com/NickWaterton/Roomba980-Python
Author: UNKNOWN
Author-email: nick.waterton@med.ge.com
License: MIT
Platform: UNKNOWN
